psenet_text_detector/__init__.py
psenet_text_detector/predict.py
psenet_text_detector/pypse.py
psenet_text_detector/utils.py
psenet_text_detector/models/__init__.py
psenet_text_detector/models/fpn_resnet.py
psenet_text_detector-0.1.1.dist-info/LICENSE
psenet_text_detector-0.1.1.dist-info/METADATA
psenet_text_detector-0.1.1.dist-info/WHEEL
psenet_text_detector-0.1.1.dist-info/top_level.txt
psenet_text_detector-0.1.1.dist-info/RECORD
