Metadata-Version: 2.1
Name: psenet-text-detector
Version: 0.1.1
Summary: Fast and accurate text detection library built on PSENet implementation
Home-page: https://github.com/fcakyon/psenet_text_detector
Author: Fatih Cagatay Akyon
License: MIT
Platform: UNKNOWN
Classifier: License :: OSI Approved :: MIT License
Classifier: Operating System :: OS Independent
Classifier: Intended Audience :: Developers
Classifier: Intended Audience :: Science/Research
Classifier: Programming Language :: Python :: 3
Classifier: Programming Language :: Python :: 3.5
Classifier: Programming Language :: Python :: 3.6
Classifier: Programming Language :: Python :: 3.7
Classifier: Programming Language :: Python :: 3.8
Classifier: Topic :: Software Development :: Libraries
Classifier: Topic :: Software Development :: Libraries :: Python Modules
Requires-Python: >=3.5
Requires-Dist: torch (>=1.0.1)
Requires-Dist: torchvision (>=0.2.1)
Requires-Dist: opencv-python (==3.4.8.29)
Requires-Dist: gdown (>=3.10.1)
